ai_scientist/__init__.py
ai_scientist/run_research.py
ai_scientist/assets/prompts/mistake_prompt.txt
ai_scientist/assets/prompts/research_prompt.txt
ai_scientist-0.1.0.dist-info/LICENSE
ai_scientist-0.1.0.dist-info/METADATA
ai_scientist-0.1.0.dist-info/WHEEL
ai_scientist-0.1.0.dist-info/entry_points.txt
ai_scientist-0.1.0.dist-info/top_level.txt
ai_scientist-0.1.0.dist-info/RECORD
