Metadata-Version: 2.1
Name: ai-scientist
Version: 0.1.0
Summary: A CLI tool for running AI-powered research tasks.
Author: Core Francisco Park
Author-email: cfpark00@gmail.com
License-File: LICENSE
Requires-Dist: openai
